controller.v
`timescale 1ns/1ns
  

  module controller(CON,op_code,clk,clr);

   output reg [17:0]CON;
   input clk;
   input clr;
   input [2:0]op_code;
   reg [5:0]state;

  parameter  AND= 3'b000,
             ADD= 3'b001,
             LDA= 3'b010,
             STA= 3'b011,
             BUN= 3'b100,
             BSA= 3'b101,
             ISZ= 3'b110,
	     HLT= 3'b111;

    always @(posedge clk,posedge clr)  
    begin
     if(clr)
        begin state <= 6'd1; end
     else if(state == 6'd32)
        begin state <= 6'd1; end
     else
       begin state <= state << 1; end
    end

  always @(state,clr)
  begin
   if(!clr)
    begin
    case(state)
     6'd1 : begin CON = 18'h09002; end 
     6'd2 : begin CON = 18'h10807; end 
     6'd4 : begin CON = 18'h08005; end 
    // 6'd8 : begin CON = 18'h09007; end 

     6'd8 : begin
            if(op_code == AND || op_code == ADD || op_code == LDA || op_code == ISZ)     
              begin CON = 18'h01407; end 
           else if(op_code == STA)   
             begin CON = 18'h02004; end
           else if(op_code == BUN)     
	     begin CON = 18'h20001; end
	   else if(op_code == BSA)
             begin CON = 18'h07402; end
	   else if(op_code == HLT)
	     begin   $stop;
                       end
           end

   6'd16 : begin
           if(op_code == LDA)        // LDA
             begin 
	      
	      CON = 18'h00103; end  
	      else if(op_code == ADD || op_code ==AND) begin
		      CON = 18'H00100; end
             else if( op_code == STA || op_code == BUN)      // ADD + AND	
             begin 
	        
		CON = 18'h0; end
           else if(op_code == BSA)      //BSA
             begin CON = 18'h20001; end
	   else if(op_code == ISZ)
	     begin CON = 18'h00200; end
           end
    
   6'd32 : begin
            if(op_code == ISZ)
               begin CON = 18'h02003; end
	    else if(op_code == ADD || op_code == AND) begin
		   
		   CON = 18'h0; end
            end
   default: $display($time,"output come in next state",state,clr,clk,op_code); 
  endcase
 end 
else begin CON = 18'h0; end 

 end
endmodule

reg8.v



  `timescale 1ns/1ns
 module IN_OUT_REG(
            output reg[7:0]REG_OUT,
            input [7:0]REG_IN,
            input CLK,LD );
 
 
 always @(posedge CLK)
 begin
  if(LD)
    REG_OUT = REG_IN;
  else
    REG_OUT = REG_OUT;
  end
 endmodule

alu.v



 module ALU(
                input [15:0]from_AC, from_DR,
                input [7:0] from_INPR,
		input clk,enable,
                input [2:0]con_signals,
                output [15:0] ALU_out,
                output reg E	);

   reg [15:0]AC;
   reg Cout;

    always @(posedge clk) begin
       E <= Cout; end
        
     always @(*) begin
        case(con_signals)
            3'd0 : AC = from_AC & from_DR ;
            3'd1 : {Cout,AC} = from_AC + from_DR;
            3'd2 : AC =  from_DR;
            3'd3 : AC = ~from_AC;
            3'd4 : AC = from_AC >> E;
            3'd5 : AC = from_AC << E;
            3'd6 : AC = 16'd0;
            3'd7 : AC = from_AC + 1;
        endcase
       end 
      //  assign ALU_out = enable ? AC : ALU_out ;
           assign ALU_out = AC;
  endmodule

memory.v


  
 module MEMORY( input [15:0]DATA_IN,
             input WRITE, READ, CLK,
             input [11:0]ADDRESS,
             output [15:0] DATA_OUT );


 reg [15:0] mem [0:4095] ;

  initial begin
	    $readmemh("memory.txt",mem,0,4095);
          end

   
	  assign DATA_OUT = READ ? mem[ADDRESS] : DATA_OUT ; 

  always @(posedge CLK) begin
  // if(READ)
    // DATA_OUT <= mem[ADDRESS];
   if(WRITE) 
     mem[ADDRESS] <=  DATA_IN;
   end

 endmodule

reg16.v


 module reg16_INR (
  output reg [15:0]to_BUS,
  input INR,
  input CLK,
  input CLR,
  input LD,
  input [15:0]from_BUS );
  
  reg [15:0]tempc ;

  //assign to_BUS = tempc;

  always @(posedge CLK) 
    begin
     if(CLR == 1)
      to_BUS <= 16'd0;
     else if(LD == 1)
      to_BUS <= from_BUS;
     else if(INR == 1)
       to_BUS = to_BUS + 1;
     else
        to_BUS = to_BUS;
    end
  endmodule

inst_reg.v


 `timescale 1ns/1ns
 module INST_REG(
            output reg[11:0]INST_OUT12,
	    output reg[2:0]INST_OUT3,
	    output reg I,
            input [15:0]REG_IN,
            input CLK,LD );
   //reg [15:0]temp;

 always @(posedge CLK)

  if(LD)
    {I,INST_OUT3,INST_OUT12} <= REG_IN;
  endmodule

pc.v


 module pc_reg (
  output reg[11:0]to_BUS,
  input INR,
  input CLK,
  input CLR,
  input LD,
  input [11:0]from_BUS );
  
  //reg [11:0]tempc ;

  //assign to_BUS = tempc;

  always @(posedge CLK, posedge CLR) 
    begin
     if(CLR == 1)
      to_BUS <= 12'd0;
     else if(LD == 1)
      to_BUS <= from_BUS;
     else if(INR == 1)
       to_BUS <= (to_BUS + 1);
     else 
	to_BUS <= to_BUS;
      end
  endmodule

main.v
 
 `include "memory.v"
 `include "pc.v"
 `include "alu.v"
 `include "inst_reg.v"
 `include "reg8.v"
 `include "reg16.v"
 `include "controller.v"


 module main(input CLK, CLR, 
             input [7:0]INPR_IN,
             output [7:0] REG_OUT,
             output E );

     wire [2:0]OUT3;
     wire [11:0]PC_out,AR_out;
     wire [17:0]CON;
     wire [7:0]INPR_out;
     wire [15:0]TR_out,DR_out,AC_out,MEM_out,IR_out,ALU_out;
     reg [15:0]bus;
     reg [17:0]CON_reg;
     wire [2:0] S;

      assign S = CON[2:0] ;
     always @(*) begin
      case({CON[2:0]})     
       3'd1 : bus = {4'd0,AR_out};
       3'd2 : bus = {4'd0,PC_out};
       3'd3 : bus = DR_out;
       3'd4 : bus = AC_out;
       3'd5 : bus = IR_out;
       3'd6 : bus = TR_out;
       3'd7 : bus = MEM_out;
     default: bus = 16'dz;
    endcase
    end
    
    pc_reg pc( PC_out, CON[16], CLK, CLR, CON[17], bus[11:0] );
    
    pc_reg AR_reg( AR_out, CON[14], CLK, CLR, CON[15], bus[11:0] );


    INST_REG IR(IR_out[11:0], IR_out[14:12], IR_out[15], bus, CLK, CON[11] );

    IN_OUT_REG INPR(INPR_out, INPR_IN, CLK, CON[3] );

    reg16_INR TR( TR_out, CON[5], CLK, CLR, CON[6], bus );
 
    reg16_INR DR( DR_out, CON[9], CLK, CLR, CON[10], bus );

    reg16_INR AC( AC_out, CON[7], CLK, CLR, CON[8], ALU_out );

    MEMORY memory( bus , CON[13], CON[12], CLK, AR_out, MEM_out );

    ALU aluuu(AC_out, DR_out, INPR_out,CLK,CON[8], IR_out[14:12] , ALU_out, E);

    IN_OUT_REG outr(REG_OUT, bus[7:0], CLK, CON[4] );

    controller cont(CON, IR_out[14:12], CLK , CLR);
   
    always @(posedge CLK, posedge CLR) begin
	    CON_reg <= CON;
    end

  endmodule

tb.v

  module test;

 reg clr,clk;
 reg [7:0]INPR_IN;
 wire [7:0]OUTR;
 wire E;
 
   main mano(clk, clr, 
             INPR_IN,
             OUTR,
             E );

 initial
  begin
   clk = 0;
   forever #5 clk = ~clk;
  end
 
  initial
   begin
    clr = 1'b0;
    @(negedge clk) clr = 1'b1;
    @(negedge clk) #1; clr = 1'b0;
    INPR_IN = 8'd7;

  end
 
  initial
   begin
   $dumpfile("s.vcd");
   $dumpvars;
  end
  initial
    #1000 $finish;
 endmodule

s.vcd
$date
	Mon Dec 13 22:42:05 2021
$end
$version
	Icarus Verilog
$end
$timescale
	1ns
$end
$scope module test $end
$var wire 8 ! OUTR [7:0] $end
$var wire 1 " E $end
$var reg 8 # INPR_IN [7:0] $end
$var reg 1 $ clk $end
$var reg 1 % clr $end
$scope module mano $end
$var wire 1 $ CLK $end
$var wire 1 % CLR $end
$var wire 8 & INPR_IN [7:0] $end
$var wire 16 ' TR_out [15:0] $end
$var wire 3 ( S [2:0] $end
$var wire 8 ) REG_OUT [7:0] $end
$var wire 12 * PC_out [11:0] $end
$var wire 16 + MEM_out [15:0] $end
$var wire 16 , IR_out [15:0] $end
$var wire 8 - INPR_out [7:0] $end
$var wire 1 " E $end
$var wire 16 . DR_out [15:0] $end
$var wire 18 / CON [17:0] $end
$var wire 12 0 AR_out [11:0] $end
$var wire 16 1 ALU_out [15:0] $end
$var wire 16 2 AC_out [15:0] $end
$var reg 18 3 CON_reg [17:0] $end
$var reg 16 4 bus [15:0] $end
$scope module AC $end
$var wire 1 $ CLK $end
$var wire 1 % CLR $end
$var wire 1 5 INR $end
$var wire 1 6 LD $end
$var wire 16 7 from_BUS [15:0] $end
$var reg 16 8 to_BUS [15:0] $end
$upscope $end
$scope module AR_reg $end
$var wire 1 $ CLK $end
$var wire 1 % CLR $end
$var wire 1 9 INR $end
$var wire 1 : LD $end
$var wire 12 ; from_BUS [11:0] $end
$var reg 12 < to_BUS [11:0] $end
$upscope $end
$scope module DR $end
$var wire 1 $ CLK $end
$var wire 1 % CLR $end
$var wire 1 = INR $end
$var wire 1 > LD $end
$var wire 16 ? from_BUS [15:0] $end
$var reg 16 @ to_BUS [15:0] $end
$upscope $end
$scope module INPR $end
$var wire 1 $ CLK $end
$var wire 1 A LD $end
$var wire 8 B REG_IN [7:0] $end
$var reg 8 C REG_OUT [7:0] $end
$upscope $end
$scope module IR $end
$var wire 1 $ CLK $end
$var wire 1 D LD $end
$var wire 16 E REG_IN [15:0] $end
$var reg 1 F I $end
$var reg 12 G INST_OUT12 [11:0] $end
$var reg 3 H INST_OUT3 [2:0] $end
$upscope $end
$scope module TR $end
$var wire 1 $ CLK $end
$var wire 1 % CLR $end
$var wire 1 I INR $end
$var wire 1 J LD $end
$var wire 16 K from_BUS [15:0] $end
$var reg 16 L to_BUS [15:0] $end
$upscope $end
$scope module aluuu $end
$var wire 16 M ALU_out [15:0] $end
$var wire 1 $ clk $end
$var wire 3 N con_signals [2:0] $end
$var wire 1 O enable $end
$var wire 16 P from_AC [15:0] $end
$var wire 16 Q from_DR [15:0] $end
$var wire 8 R from_INPR [7:0] $end
$var reg 16 S AC [15:0] $end
$var reg 1 T Cout $end
$var reg 1 " E $end
$upscope $end
$scope module cont $end
$var wire 1 $ clk $end
$var wire 1 % clr $end
$var wire 3 U op_code [2:0] $end
$var reg 18 V CON [17:0] $end
$var reg 6 W state [5:0] $end
$upscope $end
$scope module memory $end
$var wire 12 X ADDRESS [11:0] $end
$var wire 1 $ CLK $end
$var wire 16 Y DATA_IN [15:0] $end
$var wire 1 Z READ $end
$var wire 1 [ WRITE $end
$var wire 16 \ DATA_OUT [15:0] $end
$upscope $end
$scope module outr $end
$var wire 1 $ CLK $end
$var wire 1 ] LD $end
$var wire 8 ^ REG_IN [7:0] $end
$var reg 8 _ REG_OUT [7:0] $end
$upscope $end
$scope module pc $end
$var wire 1 $ CLK $end
$var wire 1 % CLR $end
$var wire 1 ` INR $end
$var wire 1 a LD $end
$var wire 12 b from_BUS [11:0] $end
$var reg 12 c to_BUS [11:0] $end
$upscope $end
$upscope $end
$upscope $end
$enddefinitions $end
#0
$dumpvars
bx c
bx b
xa
x`
bx _
bx ^
x]
bx \
x[
xZ
bx Y
bx X
bx W
bx V
bx U
xT
bx S
bx R
bx Q
bx P
xO
bx N
bx M
bx L
bx K
xJ
xI
bx H
bx G
xF
bx E
xD
bx C
bx B
xA
bx @
bx ?
x>
x=
bx <
bx ;
x:
x9
bx 8
bx 7
x6
x5
bx 4
bx 3
bx 2
bx 1
bx 0
bx /
bx .
bx -
bx ,
bx +
bx *
bx )
bx (
bx '
bx &
0%
0$
bx #
x"
bx !
$end
#5
bx0 W
1$
#10
b0 3
b1 W
b0 0
b0 <
b0 X
b0 *
b0 c
bz b
bz ;
bz ^
0]
0O
0Z
0[
06
05
0>
0=
0J
0I
0A
0D
0:
09
0a
0`
b0 (
bz 4
bz ?
bz E
bz K
bz Y
b0 /
b0 V
1%
0$
#15
b0 2
b0 8
b0 P
b0 .
b0 @
b0 Q
b0 '
b0 L
1$
#20
0$
#21
b10000000001001 +
b10000000001001 \
b0 b
b0 ;
b0 ^
1Z
1:
b10 (
b0 4
b0 ?
b0 E
b0 K
b0 Y
b1001000000000010 /
b1001000000000010 V
b111 #
b111 &
b111 B
0%
#25
b1001 b
b1001 ;
b1001 ^
0Z
1D
0:
1`
b111 (
b10000000001001 4
b10000000001001 ?
b10000000001001 E
b10000000001001 K
b10000000001001 Y
b10000100000000111 /
b10000100000000111 V
b1001000000000010 3
b10 W
1$
#30
0$
#35
b0 1
b0 7
b0 M
b0 S
0D
1:
0`
b101 (
b10 N
b10 U
b1000000000000101 /
b1000000000000101 V
0F
b10 H
b10000000001001 ,
b1001 G
b1 *
b1 c
b100 W
b10000100000000111 3
1$
#40
0$
#45
b111 b
b111 ;
b111 ^
b111 4
b111 ?
b111 E
b111 K
b111 Y
b111 +
b111 \
1Z
1>
0:
b111 (
b1010000000111 /
b1010000000111 V
b1000000000000101 3
b1000 W
b1001 0
b1001 <
b1001 X
1$
#50
0$
#55
1O
0Z
16
0>
b11 (
b111 1
b111 7
b111 M
b111 S
b100000011 /
b100000011 V
b111 .
b111 @
b111 Q
b10000 W
b1010000000111 3
1$
#60
0$
#65
b111 2
b111 8
b111 P
b100000011 3
b100000 W
1$
#70
0$
#75
b1 b
b1 ;
b1 ^
0O
1Z
06
1:
b10 (
b1 4
b1 ?
b1 E
b1 K
b1 Y
b1001000000000010 /
b1001000000000010 V
b1 W
1$
#80
0$
#85
b10111 b
b10111 ;
b10111 ^
0Z
1D
0:
1`
b111 (
b1000000010111 4
b1000000010111 ?
b1000000010111 E
b1000000010111 K
b1000000010111 Y
b10000100000000111 /
b10000100000000111 V
b1000000010111 +
b1000000010111 \
b1001000000000010 3
b10 W
b1 0
b1 <
b1 X
1$
#90
0$
#95
0T
b1110 1
b1110 7
b1110 M
b1110 S
0D
1:
0`
b101 (
b1 N
b1 U
b1000000000000101 /
b1000000000000101 V
b1 H
b1000000010111 ,
b10111 G
b10 *
b10 c
b100 W
b10000100000000111 3
1$
#100
0$
#105
b1000 b
b1000 ;
b1000 ^
b1000 4
b1000 ?
b1000 E
b1000 K
b1000 Y
b1000 +
b1000 \
1Z
1>
0:
b111 (
b1010000000111 /
b1010000000111 V
0"
b1000000000000101 3
b1000 W
b10111 0
b10111 <
b10111 X
1$
#110
0$
#115
bz b
bz ;
bz ^
1O
0Z
16
0>
b0 (
b1111 1
b1111 7
b1111 M
b1111 S
bz 4
bz ?
bz E
bz K
bz Y
b100000000 /
b100000000 V
b1000 .
b1000 @
b1000 Q
b10000 W
b1010000000111 3
1$
#120
0$
#125
0O
06
b10111 1
b10111 7
b10111 M
b10111 S
b0 /
b0 V
b1111 2
b1111 8
b1111 P
b100000000 3
b100000 W
1$
#130
0$
#135
b10 b
b10 ;
b10 ^
1Z
1:
b10 (
b10 4
b10 ?
b10 E
b10 K
b10 Y
b1001000000000010 /
b1001000000000010 V
b1 W
b0 3
1$
#140
0$
#145
b111 b
b111 ;
b111 ^
0Z
1D
0:
1`
b111 (
b111 4
b111 ?
b111 E
b111 K
b111 Y
b10000100000000111 /
b10000100000000111 V
b111 +
b111 \
b1001000000000010 3
b10 W
b10 0
b10 <
b10 X
1$
#150
0$
#155
b1000 1
b1000 7
b1000 M
b1000 S
0D
1:
0`
b101 (
b0 N
b0 U
b1000000000000101 /
b1000000000000101 V
b0 H
b111 ,
b111 G
b11 *
b11 c
b100 W
b10000100000000111 3
1$
#160
0$
#165
b1111 b
b1111 ;
b1111 ^
b1111000000001111 4
b1111000000001111 ?
b1111000000001111 E
b1111000000001111 K
b1111000000001111 Y
b1111000000001111 +
b1111000000001111 \
1Z
1>
0:
b111 (
b1010000000111 /
b1010000000111 V
b1000000000000101 3
b1000 W
b111 0
b111 <
b111 X
1$
#170
0$
#175
bz b
bz ;
bz ^
1O
0Z
16
0>
b0 (
b1111 1
b1111 7
b1111 M
b1111 S
bz 4
bz ?
bz E
bz K
bz Y
b100000000 /
b100000000 V
b1111000000001111 .
b1111000000001111 @
b1111000000001111 Q
b10000 W
b1010000000111 3
1$
#180
0$
#185
0O
06
b0 /
b0 V
b100000000 3
b100000 W
1$
#190
0$
#195
b11 b
b11 ;
b11 ^
1Z
1:
b10 (
b11 4
b11 ?
b11 E
b11 K
b11 Y
b1001000000000010 /
b1001000000000010 V
b1 W
b0 3
1$
#200
0$
#205
b110 b
b110 ;
b110 ^
0Z
1D
0:
1`
b111 (
b11000000000110 4
b11000000000110 ?
b11000000000110 E
b11000000000110 K
b11000000000110 Y
b10000100000000111 /
b10000100000000111 V
b11000000000110 +
b11000000000110 \
b1001000000000010 3
b10 W
b11 0
b11 <
b11 X
1$
#210
0$
#215
b1111111111110000 1
b1111111111110000 7
b1111111111110000 M
b1111111111110000 S
0D
1:
0`
b101 (
b11 N
b11 U
b1000000000000101 /
b1000000000000101 V
b11 H
b11000000000110 ,
b110 G
b100 *
b100 c
b100 W
b10000100000000111 3
1$
#220
0$
#225
b1111 b
b1111 ;
b1111 ^
1[
0:
b100 (
b1111 4
b1111 ?
b1111 E
b1111 K
b1111 Y
b10000000000100 /
b10000000000100 V
b1000000000000101 3
b1000 W
b110 0
b110 <
b110 X
1$
#230
0$
#235
bz b
bz ;
bz ^
0[
b0 (
bz 4
bz ?
bz E
bz K
bz Y
b0 /
b0 V
b10000 W
b10000000000100 3
1$
#240
0$
#245
b0 3
b100000 W
1$
#250
0$
#255
b1111 +
b1111 \
b100 b
b100 ;
b100 ^
1Z
1:
b10 (
b100 4
b100 ?
b100 E
b100 K
b100 Y
b1001000000000010 /
b1001000000000010 V
b1 W
1$
#260
0$
#265
b1011 b
b1011 ;
b1011 ^
0Z
1D
0:
1`
b111 (
b100000000001011 4
b100000000001011 ?
b100000000001011 E
b100000000001011 K
b100000000001011 Y
b10000100000000111 /
b10000100000000111 V
b100000000001011 +
b100000000001011 \
b1001000000000010 3
b10 W
b100 0
b100 <
b100 X
1$
#270
0$
#275
b1111 1
b1111 7
b1111 M
b1111 S
0D
1:
0`
b101 (
b100 N
b100 U
b1000000000000101 /
b1000000000000101 V
b100 H
b100000000001011 ,
b1011 G
b101 *
b101 c
b100 W
b10000100000000111 3
1$
#280
0$
#285
0:
1a
b1 (
b1011 4
b1011 ?
b1011 E
b1011 K
b1011 Y
b100000000000000001 /
b100000000000000001 V
b1000000000000101 3
b1000 W
b1011 0
b1011 <
b1011 X
1$
#290
0$
#295
bz b
bz ;
bz ^
0a
b0 (
bz 4
bz ?
bz E
bz K
bz Y
b0 /
b0 V
b1011 *
b1011 c
b10000 W
b100000000000000001 3
1$
#300
0$
#305
b0 3
b100000 W
1$
#310
0$
#315
b1000000010111 +
b1000000010111 \
b1011 b
b1011 ;
b1011 ^
1Z
1:
b10 (
b1011 4
b1011 ?
b1011 E
b1011 K
b1011 Y
b1001000000000010 /
b1001000000000010 V
b1 W
1$
#320
0$
#325
b10111 b
b10111 ;
b10111 ^
0Z
1D
0:
1`
b111 (
b1000000010111 4
b1000000010111 ?
b1000000010111 E
b1000000010111 K
b1000000010111 Y
b10000100000000111 /
b10000100000000111 V
b1001000000000010 3
b10 W
1$
#330
0$
#335
b1111000000011110 1
b1111000000011110 7
b1111000000011110 M
b1111000000011110 S
0D
1:
0`
b101 (
b1 N
b1 U
b1000000000000101 /
b1000000000000101 V
b1 H
b1000000010111 ,
b10111 G
b1100 *
b1100 c
b100 W
b10000100000000111 3
1$
#340
0$
#345
b1000 b
b1000 ;
b1000 ^
b1000 4
b1000 ?
b1000 E
b1000 K
b1000 Y
b1000 +
b1000 \
1Z
1>
0:
b111 (
b1010000000111 /
b1010000000111 V
b1000000000000101 3
b1000 W
b10111 0
b10111 <
b10111 X
1$
#350
0$
#355
bz b
bz ;
bz ^
1O
0Z
16
0>
b0 (
b10111 1
b10111 7
b10111 M
b10111 S
bz 4
bz ?
bz E
bz K
bz Y
b100000000 /
b100000000 V
b1000 .
b1000 @
b1000 Q
b10000 W
b1010000000111 3
1$
#360
0$
#365
0O
06
b11111 1
b11111 7
b11111 M
b11111 S
b0 /
b0 V
b10111 2
b10111 8
b10111 P
b100000000 3
b100000 W
1$
#370
0$
#375
b1100 b
b1100 ;
b1100 ^
1Z
1:
b10 (
b1100 4
b1100 ?
b1100 E
b1100 K
b1100 Y
b1001000000000010 /
b1001000000000010 V
b1 W
b0 3
1$
#380
0$
#385
b11000 b
b11000 ;
b11000 ^
0Z
1D
0:
1`
b111 (
b1000000011000 4
b1000000011000 ?
b1000000011000 E
b1000000011000 K
b1000000011000 Y
b10000100000000111 /
b10000100000000111 V
b1000000011000 +
b1000000011000 \
b1001000000000010 3
b10 W
b1100 0
b1100 <
b1100 X
1$
#390
0$
#395
0D
1:
0`
b101 (
b1000000000000101 /
b1000000000000101 V
b1000000011000 ,
b11000 G
b1101 *
b1101 c
b100 W
b10000100000000111 3
1$
#400
0$
#405
b10 b
b10 ;
b10 ^
b10 4
b10 ?
b10 E
b10 K
b10 Y
b10 +
b10 \
1Z
1>
0:
b111 (
b1010000000111 /
b1010000000111 V
b1000000000000101 3
b1000 W
b11000 0
b11000 <
b11000 X
1$
#410
0$
#415
bz b
bz ;
bz ^
1O
0Z
16
0>
b0 (
b11001 1
b11001 7
b11001 M
b11001 S
bz 4
bz ?
bz E
bz K
bz Y
b100000000 /
b100000000 V
b10 .
b10 @
b10 Q
b10000 W
b1010000000111 3
1$
#420
0$
#425
0O
06
b11011 1
b11011 7
b11011 M
b11011 S
b0 /
b0 V
b11001 2
b11001 8
b11001 P
b100000000 3
b100000 W
1$
#430
0$
#435
b1101 b
b1101 ;
b1101 ^
1Z
1:
b10 (
b1101 4
b1101 ?
b1101 E
b1101 K
b1101 Y
b1001000000000010 /
b1001000000000010 V
b1 W
b0 3
1$
#440
0$
#445
b11001 b
b11001 ;
b11001 ^
0Z
1D
0:
1`
b111 (
b1000000011001 4
b1000000011001 ?
b1000000011001 E
b1000000011001 K
b1000000011001 Y
b10000100000000111 /
b10000100000000111 V
b1000000011001 +
b1000000011001 \
b1001000000000010 3
b10 W
b1101 0
b1101 <
b1101 X
1$
#450
0$
#455
0D
1:
0`
b101 (
b1000000000000101 /
b1000000000000101 V
b1000000011001 ,
b11001 G
b1110 *
b1110 c
b100 W
b10000100000000111 3
1$
#460
0$
#465
b100 b
b100 ;
b100 ^
b100 4
b100 ?
b100 E
b100 K
b100 Y
b100 +
b100 \
1Z
1>
0:
b111 (
b1010000000111 /
b1010000000111 V
b1000000000000101 3
b1000 W
b11001 0
b11001 <
b11001 X
1$
#470
0$
#475
bz b
bz ;
bz ^
1O
0Z
16
0>
b0 (
b11101 1
b11101 7
b11101 M
b11101 S
bz 4
bz ?
bz E
bz K
bz Y
b100000000 /
b100000000 V
b100 .
b100 @
b100 Q
b10000 W
b1010000000111 3
1$
#480
0$
#485
0O
06
b100001 1
b100001 7
b100001 M
b100001 S
b0 /
b0 V
b11101 2
b11101 8
b11101 P
b100000000 3
b100000 W
1$
#490
0$
#495
b1110 b
b1110 ;
b1110 ^
1Z
1:
b10 (
b1110 4
b1110 ?
b1110 E
b1110 K
b1110 Y
b1001000000000010 /
b1001000000000010 V
b1 W
b0 3
1$
#500
0$
#505
b101 b
b101 ;
b101 ^
0Z
1D
0:
1`
b111 (
b101 4
b101 ?
b101 E
b101 K
b101 Y
b10000100000000111 /
b10000100000000111 V
b101 +
b101 \
b1001000000000010 3
b10 W
b1110 0
b1110 <
b1110 X
1$
#510
0$
#515
b100 1
b100 7
b100 M
b100 S
0D
1:
0`
b101 (
b0 N
b0 U
b1000000000000101 /
b1000000000000101 V
b0 H
b101 ,
b101 G
b1111 *
b1111 c
b100 W
b10000100000000111 3
1$
#520
0$
#525
b100 b
b100 ;
b100 ^
b101000000000100 4
b101000000000100 ?
b101000000000100 E
b101000000000100 K
b101000000000100 Y
b101000000000100 +
b101000000000100 \
1Z
1>
0:
b111 (
b1010000000111 /
b1010000000111 V
b1000000000000101 3
b1000 W
b101 0
b101 <
b101 X
1$
#530
0$
#535
bz b
bz ;
bz ^
1O
0Z
16
0>
b0 (
bz 4
bz ?
bz E
bz K
bz Y
b100000000 /
b100000000 V
b101000000000100 .
b101000000000100 @
b101000000000100 Q
b10000 W
b1010000000111 3
1$
#540
0$
#545
0O
06
b0 /
b0 V
b100 2
b100 8
b100 P
b100000000 3
b100000 W
1$
#550
0$
#555
b1111 b
b1111 ;
b1111 ^
1Z
1:
b10 (
b1111 4
b1111 ?
b1111 E
b1111 K
b1111 Y
b1001000000000010 /
b1001000000000010 V
b1 W
b0 3
1$
#560
0$
#565
b111 b
b111 ;
b111 ^
0Z
1D
0:
1`
b111 (
b111 4
b111 ?
b111 E
b111 K
b111 Y
b10000100000000111 /
b10000100000000111 V
b111 +
b111 \
b1001000000000010 3
b10 W
b1111 0
b1111 <
b1111 X
1$
#570
0$
#575
0D
1:
0`
b101 (
b1000000000000101 /
b1000000000000101 V
b111 ,
b111 G
b10000 *
b10000 c
b100 W
b10000100000000111 3
1$
#580
0$
#585
b1111 b
b1111 ;
b1111 ^
b1111000000001111 4
b1111000000001111 ?
b1111000000001111 E
b1111000000001111 K
b1111000000001111 Y
b1111000000001111 +
b1111000000001111 \
1Z
1>
0:
b111 (
b1010000000111 /
b1010000000111 V
b1000000000000101 3
b1000 W
b111 0
b111 <
b111 X
1$
#590
0$
#595
bz b
bz ;
bz ^
1O
0Z
16
0>
b0 (
bz 4
bz ?
bz E
bz K
bz Y
b100000000 /
b100000000 V
b1111000000001111 .
b1111000000001111 @
b1111000000001111 Q
b10000 W
b1010000000111 3
1$
#600
0$
#605
0O
06
b0 /
b0 V
b100000000 3
b100000 W
1$
#610
0$
#615
b10000 b
b10000 ;
b10000 ^
1Z
1:
b10 (
b10000 4
b10000 ?
b10000 E
b10000 K
b10000 Y
b1001000000000010 /
b1001000000000010 V
b1 W
b0 3
1$
#620
0$
#625
b0 b
b0 ;
b0 ^
0Z
1D
0:
1`
b111 (
b111000000000000 4
b111000000000000 ?
b111000000000000 E
b111000000000000 K
b111000000000000 Y
b10000100000000111 /
b10000100000000111 V
b111000000000000 +
b111000000000000 \
b1001000000000010 3
b10 W
b10000 0
b10000 <
b10000 X
1$
#630
0$
#635
b101 1
b101 7
b101 M
b101 S
0D
1:
0`
b101 (
b111 N
b111 U
b1000000000000101 /
b1000000000000101 V
b111 H
b111000000000000 ,
b0 G
b10001 *
b10001 c
b100 W
b10000100000000111 3
1$
